{"config":{"output_file":null,"full_docs":false,"pub_only":false,"reachable_only":false,"distro_crate":false,"signatures":false,"borrow_data":false},"version":"0.19.1","compilation":{"directory":"/Users/trevorschirra/Documents/GitHub/Graph_Stuff/disjoint_sets/generic_usize_graph","program":"/Users/trevorschirra/.rustup/toolchains/stable-x86_64-apple-darwin/bin/rls","arguments":[],"output":"/Users/trevorschirra/Documents/GitHub/Graph_Stuff/disjoint_sets/generic_usize_graph/target/rls/debug/deps/libgeneric_usize_graph-dff8b6711e10f35f.rmeta"},"prelude":{"crate_id":{"name":"generic_usize_graph","disambiguator":[5060927255953840092,1164377942615257508]},"crate_root":"src","external_crates":[{"file_name":"/Users/trevorschirra/Documents/GitHub/Graph_Stuff/disjoint_sets/generic_usize_graph/src/main.rs","num":1,"id":{"name":"std","disambiguator":[14497711731351875891,7574154950596153320]}},{"file_name":"/Users/trevorschirra/Documents/GitHub/Graph_Stuff/disjoint_sets/generic_usize_graph/src/main.rs","num":2,"id":{"name":"core","disambiguator":[17161976177339802527,9637120080719870273]}},{"file_name":"/Users/trevorschirra/Documents/GitHub/Graph_Stuff/disjoint_sets/generic_usize_graph/src/main.rs","num":3,"id":{"name":"compiler_builtins","disambiguator":[12784072134307519025,4657485898025748013]}},{"file_name":"/Users/trevorschirra/Documents/GitHub/Graph_Stuff/disjoint_sets/generic_usize_graph/src/main.rs","num":4,"id":{"name":"rustc_std_workspace_core","disambiguator":[8860544973196061204,9932137894390183628]}},{"file_name":"/Users/trevorschirra/Documents/GitHub/Graph_Stuff/disjoint_sets/generic_usize_graph/src/main.rs","num":5,"id":{"name":"alloc","disambiguator":[15484098214765895148,4360652648143560453]}},{"file_name":"/Users/trevorschirra/Documents/GitHub/Graph_Stuff/disjoint_sets/generic_usize_graph/src/main.rs","num":6,"id":{"name":"libc","disambiguator":[13802683045354889200,17279120461159080731]}},{"file_name":"/Users/trevorschirra/Documents/GitHub/Graph_Stuff/disjoint_sets/generic_usize_graph/src/main.rs","num":7,"id":{"name":"unwind","disambiguator":[13733846401634403672,16568137600355934567]}},{"file_name":"/Users/trevorschirra/Documents/GitHub/Graph_Stuff/disjoint_sets/generic_usize_graph/src/main.rs","num":8,"id":{"name":"cfg_if","disambiguator":[5926527291982439463,7261863668131194074]}},{"file_name":"/Users/trevorschirra/Documents/GitHub/Graph_Stuff/disjoint_sets/generic_usize_graph/src/main.rs","num":9,"id":{"name":"hashbrown","disambiguator":[2147386378482378397,1448349958257004752]}},{"file_name":"/Users/trevorschirra/Documents/GitHub/Graph_Stuff/disjoint_sets/generic_usize_graph/src/main.rs","num":10,"id":{"name":"rustc_std_workspace_alloc","disambiguator":[8504510625746843556,11549570195915831773]}},{"file_name":"/Users/trevorschirra/Documents/GitHub/Graph_Stuff/disjoint_sets/generic_usize_graph/src/main.rs","num":11,"id":{"name":"rustc_demangle","disambiguator":[1145582961014725186,16562354883654090131]}},{"file_name":"/Users/trevorschirra/Documents/GitHub/Graph_Stuff/disjoint_sets/generic_usize_graph/src/main.rs","num":12,"id":{"name":"std_detect","disambiguator":[6582153069738696943,14519107576634371424]}},{"file_name":"/Users/trevorschirra/Documents/GitHub/Graph_Stuff/disjoint_sets/generic_usize_graph/src/main.rs","num":13,"id":{"name":"addr2line","disambiguator":[15498041504304623936,9266600846380482125]}},{"file_name":"/Users/trevorschirra/Documents/GitHub/Graph_Stuff/disjoint_sets/generic_usize_graph/src/main.rs","num":14,"id":{"name":"gimli","disambiguator":[12608136573466536856,1503974727608604885]}},{"file_name":"/Users/trevorschirra/Documents/GitHub/Graph_Stuff/disjoint_sets/generic_usize_graph/src/main.rs","num":15,"id":{"name":"object","disambiguator":[16755883997827362908,2889333423780235391]}},{"file_name":"/Users/trevorschirra/Documents/GitHub/Graph_Stuff/disjoint_sets/generic_usize_graph/src/main.rs","num":16,"id":{"name":"panic_unwind","disambiguator":[3009561993154964965,13259943199418826037]}}],"span":{"file_name":"src/main.rs","byte_start":0,"byte_end":3003,"line_start":1,"line_end":119,"column_start":1,"column_end":2}},"imports":[],"defs":[{"kind":"Mod","id":{"krate":0,"index":0},"span":{"file_name":"src/main.rs","byte_start":0,"byte_end":3003,"line_start":1,"line_end":119,"column_start":1,"column_end":2},"name":"","qualname":"::","value":"src/main.rs","parent":null,"children":[{"krate":0,"index":1},{"krate":0,"index":2},{"krate":0,"index":3},{"krate":0,"index":5},{"krate":0,"index":9},{"krate":0,"index":13},{"krate":0,"index":18},{"krate":0,"index":22},{"krate":0,"index":30}],"decl_id":null,"docs":"","sig":null,"attributes":[]},{"kind":"Struct","id":{"krate":0,"index":3},"span":{"file_name":"src/main.rs","byte_start":7,"byte_end":19,"line_start":1,"line_end":1,"column_start":8,"column_end":20},"name":"DisjointSets","qualname":"::DisjointSets","value":"DisjointSets { parent }","parent":null,"children":[{"krate":0,"index":4}],"decl_id":null,"docs":"","sig":null,"attributes":[]},{"kind":"Field","id":{"krate":0,"index":4},"span":{"file_name":"src/main.rs","byte_start":26,"byte_end":32,"line_start":2,"line_end":2,"column_start":5,"column_end":11},"name":"parent","qualname":"::DisjointSets::parent","value":"std::vec::Vec<usize>","parent":{"krate":0,"index":3},"children":[],"decl_id":null,"docs":"","sig":null,"attributes":[]},{"kind":"Local","id":{"krate":0,"index":1073741830},"span":{"file_name":"src/main.rs","byte_start":80,"byte_end":84,"line_start":6,"line_end":6,"column_start":12,"column_end":16},"name":"size","qualname":"<DisjointSets>::new::size","value":"usize","parent":null,"children":[],"decl_id":null,"docs":"","sig":null,"attributes":[]},{"kind":"Method","id":{"krate":0,"index":6},"span":{"file_name":"src/main.rs","byte_start":76,"byte_end":79,"line_start":6,"line_end":6,"column_start":8,"column_end":11},"name":"new","qualname":"<DisjointSets>::new","value":"fn new(usize) -> Self","parent":null,"children":[],"decl_id":null,"docs":"","sig":null,"attributes":[]},{"kind":"Local","id":{"krate":0,"index":1073741831},"span":{"file_name":"src/main.rs","byte_start":193,"byte_end":197,"line_start":12,"line_end":12,"column_start":18,"column_end":22},"name":"self","qualname":"<DisjointSets>::find::self","value":"&mut DisjointSets","parent":null,"children":[],"decl_id":null,"docs":"","sig":null,"attributes":[]},{"kind":"Local","id":{"krate":0,"index":536870919},"span":{"file_name":"src/main.rs","byte_start":199,"byte_end":206,"line_start":12,"line_end":12,"column_start":24,"column_end":31},"name":"element","qualname":"<DisjointSets>::find::element","value":"usize","parent":null,"children":[],"decl_id":null,"docs":"","sig":null,"attributes":[]},{"kind":"Method","id":{"krate":0,"index":7},"span":{"file_name":"src/main.rs","byte_start":183,"byte_end":187,"line_start":12,"line_end":12,"column_start":8,"column_end":12},"name":"find","qualname":"<DisjointSets>::find","value":"fn find(&mut Self, usize) -> usize","parent":null,"children":[],"decl_id":null,"docs":"","sig":null,"attributes":[]},{"kind":"Local","id":{"krate":0,"index":805306375},"span":{"file_name":"src/main.rs","byte_start":238,"byte_end":255,"line_start":13,"line_end":13,"column_start":13,"column_end":30},"name":"parent_of_element","qualname":"parent_of_element$HirId { owner: DefId(0:7 ~ generic_usize_graph[463c]::{impl#0}::find), local_id: 12 }","value":"usize","parent":null,"children":[],"decl_id":null,"docs":"","sig":null,"attributes":[]},{"kind":"Local","id":{"krate":0,"index":1073741832},"span":{"file_name":"src/main.rs","byte_start":460,"byte_end":464,"line_start":21,"line_end":21,"column_start":19,"column_end":23},"name":"self","qualname":"<DisjointSets>::merge::self","value":"&mut DisjointSets","parent":null,"children":[],"decl_id":null,"docs":"","sig":null,"attributes":[]},{"kind":"Local","id":{"krate":0,"index":536870920},"span":{"file_name":"src/main.rs","byte_start":467,"byte_end":468,"line_start":21,"line_end":21,"column_start":26,"column_end":27},"name":"u","qualname":"<DisjointSets>::merge::u","value":"usize","parent":null,"children":[],"decl_id":null,"docs":"","sig":null,"attributes":[]},{"kind":"Local","id":{"krate":0,"index":2684354568},"span":{"file_name":"src/main.rs","byte_start":470,"byte_end":471,"line_start":21,"line_end":21,"column_start":29,"column_end":30},"name":"v","qualname":"<DisjointSets>::merge::v","value":"usize","parent":null,"children":[],"decl_id":null,"docs":"","sig":null,"attributes":[]},{"kind":"Method","id":{"krate":0,"index":8},"span":{"file_name":"src/main.rs","byte_start":449,"byte_end":454,"line_start":21,"line_end":21,"column_start":8,"column_end":13},"name":"merge","qualname":"<DisjointSets>::merge","value":"fn merge(&mut Self, (usize, usize)) -> bool","parent":null,"children":[],"decl_id":null,"docs":"","sig":null,"attributes":[]},{"kind":"Local","id":{"krate":0,"index":2818572296},"span":{"file_name":"src/main.rs","byte_start":513,"byte_end":524,"line_start":22,"line_end":22,"column_start":14,"column_end":25},"name":"parent_of_u","qualname":"parent_of_u$HirId { owner: DefId(0:8 ~ generic_usize_graph[463c]::{impl#0}::merge), local_id: 21 }","value":"usize","parent":null,"children":[],"decl_id":null,"docs":"","sig":null,"attributes":[]},{"kind":"Local","id":{"krate":0,"index":1744830472},"span":{"file_name":"src/main.rs","byte_start":526,"byte_end":537,"line_start":22,"line_end":22,"column_start":27,"column_end":38},"name":"parent_of_v","qualname":"parent_of_v$HirId { owner: DefId(0:8 ~ generic_usize_graph[463c]::{impl#0}::merge), local_id: 22 }","value":"usize","parent":null,"children":[],"decl_id":null,"docs":"","sig":null,"attributes":[]},{"kind":"Struct","id":{"krate":0,"index":9},"span":{"file_name":"src/main.rs","byte_start":671,"byte_end":692,"line_start":29,"line_end":29,"column_start":8,"column_end":29},"name":"AdjacencyListIterator","qualname":"::AdjacencyListIterator","value":"AdjacencyListIterator { graph, next_edge }","parent":null,"children":[{"krate":0,"index":11},{"krate":0,"index":12}],"decl_id":null,"docs":"","sig":null,"attributes":[]},{"kind":"Field","id":{"krate":0,"index":11},"span":{"file_name":"src/main.rs","byte_start":703,"byte_end":708,"line_start":30,"line_end":30,"column_start":5,"column_end":10},"name":"graph","qualname":"::AdjacencyListIterator::graph","value":"&'a Graph","parent":{"krate":0,"index":9},"children":[],"decl_id":null,"docs":"","sig":null,"attributes":[]},{"kind":"Field","id":{"krate":0,"index":12},"span":{"file_name":"src/main.rs","byte_start":725,"byte_end":734,"line_start":31,"line_end":31,"column_start":5,"column_end":14},"name":"next_edge","qualname":"::AdjacencyListIterator::next_edge","value":"std::option::Option<usize>","parent":{"krate":0,"index":9},"children":[],"decl_id":null,"docs":"","sig":null,"attributes":[]},{"kind":"Local","id":{"krate":0,"index":1073741840},"span":{"file_name":"src/main.rs","byte_start":854,"byte_end":858,"line_start":37,"line_end":37,"column_start":18,"column_end":22},"name":"self","qualname":"<AdjacencyListIterator as std::iter::Iterator>::next::self","value":"&mut AdjacencyListIterator","parent":null,"children":[],"decl_id":null,"docs":"","sig":null,"attributes":[]},{"kind":"Method","id":{"krate":0,"index":16},"span":{"file_name":"src/main.rs","byte_start":844,"byte_end":848,"line_start":37,"line_end":37,"column_start":8,"column_end":12},"name":"next","qualname":"<AdjacencyListIterator as std::iter::Iterator>::next","value":"fn next(&mut Self) -> Option<Self::Item>","parent":{"krate":2,"index":7233},"children":[],"decl_id":{"krate":2,"index":7235},"docs":"","sig":null,"attributes":[]},{"kind":"Local","id":{"krate":0,"index":268435472},"span":{"file_name":"src/main.rs","byte_start":912,"byte_end":916,"line_start":38,"line_end":38,"column_start":29,"column_end":33},"name":"edge","qualname":"$HirId { owner: DefId(0:16 ~ generic_usize_graph[463c]::{impl#1}::next), local_id: 39 }::edge","value":"usize","parent":null,"children":[],"decl_id":null,"docs":"","sig":null,"attributes":[]},{"kind":"Local","id":{"krate":0,"index":2281701392},"span":{"file_name":"src/main.rs","byte_start":936,"byte_end":942,"line_start":39,"line_end":39,"column_start":17,"column_end":23},"name":"vertex","qualname":"vertex$HirId { owner: DefId(0:16 ~ generic_usize_graph[463c]::{impl#1}::next), local_id: 17 }","value":"usize","parent":null,"children":[],"decl_id":null,"docs":"","sig":null,"attributes":[]},{"kind":"Struct","id":{"krate":0,"index":18},"span":{"file_name":"src/main.rs","byte_start":1092,"byte_end":1097,"line_start":46,"line_end":46,"column_start":8,"column_end":13},"name":"Graph","qualname":"::Graph","value":"Graph { vertex_to_edge, edge_to_edge, edge_to_vertex }","parent":null,"children":[{"krate":0,"index":19},{"krate":0,"index":20},{"krate":0,"index":21}],"decl_id":null,"docs":"","sig":null,"attributes":[]},{"kind":"Field","id":{"krate":0,"index":19},"span":{"file_name":"src/main.rs","byte_start":1104,"byte_end":1118,"line_start":47,"line_end":47,"column_start":5,"column_end":19},"name":"vertex_to_edge","qualname":"::Graph::vertex_to_edge","value":"std::vec::Vec<std::option::Option<usize>>","parent":{"krate":0,"index":18},"children":[],"decl_id":null,"docs":"","sig":null,"attributes":[]},{"kind":"Field","id":{"krate":0,"index":20},"span":{"file_name":"src/main.rs","byte_start":1144,"byte_end":1156,"line_start":48,"line_end":48,"column_start":5,"column_end":17},"name":"edge_to_edge","qualname":"::Graph::edge_to_edge","value":"std::vec::Vec<std::option::Option<usize>>","parent":{"krate":0,"index":18},"children":[],"decl_id":null,"docs":"","sig":null,"attributes":[]},{"kind":"Field","id":{"krate":0,"index":21},"span":{"file_name":"src/main.rs","byte_start":1182,"byte_end":1196,"line_start":49,"line_end":49,"column_start":5,"column_end":19},"name":"edge_to_vertex","qualname":"::Graph::edge_to_vertex","value":"std::vec::Vec<usize>","parent":{"krate":0,"index":18},"children":[],"decl_id":null,"docs":"","sig":null,"attributes":[]},{"kind":"Local","id":{"krate":0,"index":1073741847},"span":{"file_name":"src/main.rs","byte_start":1237,"byte_end":1249,"line_start":53,"line_end":53,"column_start":12,"column_end":24},"name":"max_vertices","qualname":"<Graph>::new::max_vertices","value":"usize","parent":null,"children":[],"decl_id":null,"docs":"","sig":null,"attributes":[]},{"kind":"Local","id":{"krate":0,"index":536870935},"span":{"file_name":"src/main.rs","byte_start":1258,"byte_end":1271,"line_start":53,"line_end":53,"column_start":33,"column_end":46},"name":"max_edges_est","qualname":"<Graph>::new::max_edges_est","value":"usize","parent":null,"children":[],"decl_id":null,"docs":"","sig":null,"attributes":[]},{"kind":"Method","id":{"krate":0,"index":23},"span":{"file_name":"src/main.rs","byte_start":1233,"byte_end":1236,"line_start":53,"line_end":53,"column_start":8,"column_end":11},"name":"new","qualname":"<Graph>::new","value":"fn new(usize, usize) -> Self","parent":null,"children":[],"decl_id":null,"docs":"","sig":null,"attributes":[]},{"kind":"Local","id":{"krate":0,"index":1073741848},"span":{"file_name":"src/main.rs","byte_start":1530,"byte_end":1534,"line_start":62,"line_end":62,"column_start":26,"column_end":30},"name":"self","qualname":"<Graph>::get_num_vertices::self","value":"&Graph","parent":null,"children":[],"decl_id":null,"docs":"","sig":null,"attributes":[]},{"kind":"Method","id":{"krate":0,"index":24},"span":{"file_name":"src/main.rs","byte_start":1512,"byte_end":1528,"line_start":62,"line_end":62,"column_start":8,"column_end":24},"name":"get_num_vertices","qualname":"<Graph>::get_num_vertices","value":"fn get_num_vertices(&Self) -> usize","parent":null,"children":[],"decl_id":null,"docs":"","sig":null,"attributes":[]},{"kind":"Local","id":{"krate":0,"index":1073741849},"span":{"file_name":"src/main.rs","byte_start":1610,"byte_end":1614,"line_start":66,"line_end":66,"column_start":23,"column_end":27},"name":"self","qualname":"<Graph>::get_num_edges::self","value":"&Graph","parent":null,"children":[],"decl_id":null,"docs":"","sig":null,"attributes":[]},{"kind":"Method","id":{"krate":0,"index":25},"span":{"file_name":"src/main.rs","byte_start":1595,"byte_end":1608,"line_start":66,"line_end":66,"column_start":8,"column_end":21},"name":"get_num_edges","qualname":"<Graph>::get_num_edges","value":"fn get_num_edges(&Self) -> usize","parent":null,"children":[],"decl_id":null,"docs":"","sig":null,"attributes":[]},{"kind":"Local","id":{"krate":0,"index":1073741850},"span":{"file_name":"src/main.rs","byte_start":1698,"byte_end":1702,"line_start":70,"line_end":70,"column_start":31,"column_end":35},"name":"self","qualname":"<Graph>::add_directed_edge::self","value":"&mut Graph","parent":null,"children":[],"decl_id":null,"docs":"","sig":null,"attributes":[]},{"kind":"Local","id":{"krate":0,"index":536870938},"span":{"file_name":"src/main.rs","byte_start":1705,"byte_end":1706,"line_start":70,"line_end":70,"column_start":38,"column_end":39},"name":"u","qualname":"<Graph>::add_directed_edge::u","value":"usize","parent":null,"children":[],"decl_id":null,"docs":"","sig":null,"attributes":[]},{"kind":"Local","id":{"krate":0,"index":2684354586},"span":{"file_name":"src/main.rs","byte_start":1708,"byte_end":1709,"line_start":70,"line_end":70,"column_start":41,"column_end":42},"name":"v","qualname":"<Graph>::add_directed_edge::v","value":"usize","parent":null,"children":[],"decl_id":null,"docs":"","sig":null,"attributes":[]},{"kind":"Method","id":{"krate":0,"index":26},"span":{"file_name":"src/main.rs","byte_start":1675,"byte_end":1692,"line_start":70,"line_end":70,"column_start":8,"column_end":25},"name":"add_directed_edge","qualname":"<Graph>::add_directed_edge","value":"fn add_directed_edge(&mut Self, (usize, usize))","parent":null,"children":[],"decl_id":null,"docs":"","sig":null,"attributes":[]},{"kind":"Local","id":{"krate":0,"index":1073741851},"span":{"file_name":"src/main.rs","byte_start":1923,"byte_end":1927,"line_start":76,"line_end":76,"column_start":33,"column_end":37},"name":"self","qualname":"<Graph>::add_undirected_edge::self","value":"&mut Graph","parent":null,"children":[],"decl_id":null,"docs":"","sig":null,"attributes":[]},{"kind":"Local","id":{"krate":0,"index":536870939},"span":{"file_name":"src/main.rs","byte_start":1930,"byte_end":1931,"line_start":76,"line_end":76,"column_start":40,"column_end":41},"name":"u","qualname":"<Graph>::add_undirected_edge::u","value":"usize","parent":null,"children":[],"decl_id":null,"docs":"","sig":null,"attributes":[]},{"kind":"Local","id":{"krate":0,"index":2684354587},"span":{"file_name":"src/main.rs","byte_start":1933,"byte_end":1934,"line_start":76,"line_end":76,"column_start":43,"column_end":44},"name":"v","qualname":"<Graph>::add_undirected_edge::v","value":"usize","parent":null,"children":[],"decl_id":null,"docs":"","sig":null,"attributes":[]},{"kind":"Method","id":{"krate":0,"index":27},"span":{"file_name":"src/main.rs","byte_start":1898,"byte_end":1917,"line_start":76,"line_end":76,"column_start":8,"column_end":27},"name":"add_undirected_edge","qualname":"<Graph>::add_undirected_edge","value":"fn add_undirected_edge(&mut Self, (usize, usize))","parent":null,"children":[],"decl_id":null,"docs":"","sig":null,"attributes":[]},{"kind":"Local","id":{"krate":0,"index":1073741852},"span":{"file_name":"src/main.rs","byte_start":2076,"byte_end":2080,"line_start":81,"line_end":81,"column_start":37,"column_end":41},"name":"self","qualname":"<Graph>::boolean_satistfiability::self","value":"&mut Graph","parent":null,"children":[],"decl_id":null,"docs":"","sig":null,"attributes":[]},{"kind":"Local","id":{"krate":0,"index":536870940},"span":{"file_name":"src/main.rs","byte_start":2082,"byte_end":2083,"line_start":81,"line_end":81,"column_start":43,"column_end":44},"name":"u","qualname":"<Graph>::boolean_satistfiability::u","value":"usize","parent":null,"children":[],"decl_id":null,"docs":"","sig":null,"attributes":[]},{"kind":"Local","id":{"krate":0,"index":1610612764},"span":{"file_name":"src/main.rs","byte_start":2092,"byte_end":2093,"line_start":81,"line_end":81,"column_start":53,"column_end":54},"name":"v","qualname":"<Graph>::boolean_satistfiability::v","value":"usize","parent":null,"children":[],"decl_id":null,"docs":"","sig":null,"attributes":[]},{"kind":"Method","id":{"krate":0,"index":28},"span":{"file_name":"src/main.rs","byte_start":2047,"byte_end":2070,"line_start":81,"line_end":81,"column_start":8,"column_end":31},"name":"boolean_satistfiability","qualname":"<Graph>::boolean_satistfiability","value":"fn boolean_satistfiability(&mut Self, usize, usize)","parent":null,"children":[],"decl_id":null,"docs":"","sig":null,"attributes":[]},{"kind":"Local","id":{"krate":0,"index":1073741853},"span":{"file_name":"src/main.rs","byte_start":2226,"byte_end":2230,"line_start":86,"line_end":86,"column_start":28,"column_end":32},"name":"self","qualname":"<Graph>::get_adjacency_list::self","value":"&Graph","parent":null,"children":[],"decl_id":null,"docs":"","sig":null,"attributes":[]},{"kind":"Local","id":{"krate":0,"index":536870941},"span":{"file_name":"src/main.rs","byte_start":2232,"byte_end":2233,"line_start":86,"line_end":86,"column_start":34,"column_end":35},"name":"u","qualname":"<Graph>::get_adjacency_list::u","value":"usize","parent":null,"children":[],"decl_id":null,"docs":"","sig":null,"attributes":[]},{"kind":"Method","id":{"krate":0,"index":29},"span":{"file_name":"src/main.rs","byte_start":2206,"byte_end":2224,"line_start":86,"line_end":86,"column_start":8,"column_end":26},"name":"get_adjacency_list","qualname":"<Graph>::get_adjacency_list","value":"fn get_adjacency_list(&Self, usize) -> AdjacencyListIterator","parent":null,"children":[],"decl_id":null,"docs":"","sig":null,"attributes":[]},{"kind":"Function","id":{"krate":0,"index":30},"span":{"file_name":"src/main.rs","byte_start":2396,"byte_end":2400,"line_start":95,"line_end":95,"column_start":4,"column_end":8},"name":"main","qualname":"::main","value":"fn main()","parent":null,"children":[],"decl_id":null,"docs":"","sig":null,"attributes":[]},{"kind":"Local","id":{"krate":0,"index":1140850718},"span":{"file_name":"src/main.rs","byte_start":2443,"byte_end":2448,"line_start":98,"line_end":98,"column_start":9,"column_end":14},"name":"edges","qualname":"edges$HirId { owner: DefId(0:30 ~ generic_usize_graph[463c]::main), local_id: 34 }","value":"std::vec::Vec<(usize, usize)>","parent":null,"children":[],"decl_id":null,"docs":"","sig":null,"attributes":[]},{"kind":"Local","id":{"krate":0,"index":872415262},"span":{"file_name":"src/main.rs","byte_start":2538,"byte_end":2543,"line_start":99,"line_end":99,"column_start":13,"column_end":18},"name":"graph","qualname":"graph$HirId { owner: DefId(0:30 ~ generic_usize_graph[463c]::main), local_id: 44 }","value":"Graph","parent":null,"children":[],"decl_id":null,"docs":"","sig":null,"attributes":[]},{"kind":"Local","id":{"krate":0,"index":1107296286},"span":{"file_name":"src/main.rs","byte_start":2579,"byte_end":2593,"line_start":100,"line_end":100,"column_start":14,"column_end":28},"name":"iter","qualname":"iter$HirId { owner: DefId(0:30 ~ generic_usize_graph[463c]::main), local_id: 66 }","value":"std::ops::Range<usize>","parent":null,"children":[],"decl_id":null,"docs":"","sig":null,"attributes":[]},{"kind":"Local","id":{"krate":0,"index":1811939358},"span":{"file_name":"src/main.rs","byte_start":2579,"byte_end":2593,"line_start":100,"line_end":100,"column_start":14,"column_end":28},"name":"__next","qualname":"__next$HirId { owner: DefId(0:30 ~ generic_usize_graph[463c]::main), local_id: 54 }","value":"usize","parent":null,"children":[],"decl_id":null,"docs":"","sig":null,"attributes":[]},{"kind":"Local","id":{"krate":0,"index":3959423006},"span":{"file_name":"src/main.rs","byte_start":2574,"byte_end":2575,"line_start":100,"line_end":100,"column_start":9,"column_end":10},"name":"val","qualname":"val$HirId { owner: DefId(0:30 ~ generic_usize_graph[463c]::main), local_id: 55 }","value":"usize","parent":null,"children":[],"decl_id":null,"docs":"","sig":null,"attributes":[]},{"kind":"Local","id":{"krate":0,"index":838860830},"span":{"file_name":"src/main.rs","byte_start":2574,"byte_end":2575,"line_start":100,"line_end":100,"column_start":9,"column_end":10},"name":"i","qualname":"i$HirId { owner: DefId(0:30 ~ generic_usize_graph[463c]::main), local_id: 76 }","value":"usize","parent":null,"children":[],"decl_id":null,"docs":"","sig":null,"attributes":[]},{"kind":"Local","id":{"krate":0,"index":3238002718},"span":{"file_name":"src/main.rs","byte_start":2759,"byte_end":2768,"line_start":108,"line_end":108,"column_start":9,"column_end":18},"name":"adjacency","qualname":"adjacency$HirId { owner: DefId(0:30 ~ generic_usize_graph[463c]::main), local_id: 131 }","value":"std::vec::Vec<(usize, usize)>","parent":null,"children":[],"decl_id":null,"docs":"","sig":null,"attributes":[]},{"kind":"Local","id":{"krate":0,"index":3942645790},"span":{"file_name":"src/main.rs","byte_start":2900,"byte_end":2909,"line_start":111,"line_end":111,"column_start":27,"column_end":36},"name":"iter","qualname":"iter$HirId { owner: DefId(0:30 ~ generic_usize_graph[463c]::main), local_id: 215 }","value":"std::vec::IntoIter<(usize, usize)>","parent":null,"children":[],"decl_id":null,"docs":"","sig":null,"attributes":[]},{"kind":"Local","id":{"krate":0,"index":3539992606},"span":{"file_name":"src/main.rs","byte_start":2900,"byte_end":2909,"line_start":111,"line_end":111,"column_start":27,"column_end":36},"name":"__next","qualname":"__next$HirId { owner: DefId(0:30 ~ generic_usize_graph[463c]::main), local_id: 203 }","value":"(usize, usize)","parent":null,"children":[],"decl_id":null,"docs":"","sig":null,"attributes":[]},{"kind":"Local","id":{"krate":0,"index":855638046},"span":{"file_name":"src/main.rs","byte_start":2882,"byte_end":2896,"line_start":111,"line_end":111,"column_start":9,"column_end":23},"name":"val","qualname":"val$HirId { owner: DefId(0:30 ~ generic_usize_graph[463c]::main), local_id: 204 }","value":"(usize, usize)","parent":null,"children":[],"decl_id":null,"docs":"","sig":null,"attributes":[]},{"kind":"Local","id":{"krate":0,"index":2264924190},"span":{"file_name":"src/main.rs","byte_start":2883,"byte_end":2887,"line_start":111,"line_end":111,"column_start":10,"column_end":14},"name":"edge","qualname":"edge$HirId { owner: DefId(0:30 ~ generic_usize_graph[463c]::main), local_id: 225 }","value":"usize","parent":null,"children":[],"decl_id":null,"docs":"","sig":null,"attributes":[]},{"kind":"Local","id":{"krate":0,"index":1191182366},"span":{"file_name":"src/main.rs","byte_start":2889,"byte_end":2895,"line_start":111,"line_end":111,"column_start":16,"column_end":22},"name":"vertex","qualname":"vertex$HirId { owner: DefId(0:30 ~ generic_usize_graph[463c]::main), local_id: 226 }","value":"usize","parent":null,"children":[],"decl_id":null,"docs":"","sig":null,"attributes":[]}],"impls":[{"id":0,"kind":"Inherent","span":{"file_name":"src/main.rs","byte_start":54,"byte_end":66,"line_start":5,"line_end":5,"column_start":6,"column_end":18},"value":"","parent":null,"children":[{"krate":0,"index":6},{"krate":0,"index":7},{"krate":0,"index":8}],"docs":"","sig":null,"attributes":[]},{"id":1,"kind":"Direct","span":{"file_name":"src/main.rs","byte_start":776,"byte_end":797,"line_start":34,"line_end":34,"column_start":23,"column_end":44},"value":"","parent":null,"children":[{"krate":0,"index":15},{"krate":0,"index":16}],"docs":"","sig":null,"attributes":[]},{"id":2,"kind":"Inherent","span":{"file_name":"src/main.rs","byte_start":1218,"byte_end":1223,"line_start":52,"line_end":52,"column_start":6,"column_end":11},"value":"","parent":null,"children":[{"krate":0,"index":23},{"krate":0,"index":24},{"krate":0,"index":25},{"krate":0,"index":26},{"krate":0,"index":27},{"krate":0,"index":28},{"krate":0,"index":29}],"docs":"","sig":null,"attributes":[]}],"refs":[{"kind":"Type","span":{"file_name":"src/main.rs","byte_start":34,"byte_end":37,"line_start":2,"line_end":2,"column_start":13,"column_end":16},"ref_id":{"krate":5,"index":6772}},{"kind":"Type","span":{"file_name":"src/main.rs","byte_start":54,"byte_end":66,"line_start":5,"line_end":5,"column_start":6,"column_end":18},"ref_id":{"krate":0,"index":3}},{"kind":"Type","span":{"file_name":"src/main.rs","byte_start":111,"byte_end":115,"line_start":7,"line_end":7,"column_start":9,"column_end":13},"ref_id":{"krate":0,"index":3}},{"kind":"Variable","span":{"file_name":"src/main.rs","byte_start":130,"byte_end":136,"line_start":8,"line_end":8,"column_start":13,"column_end":19},"ref_id":{"krate":0,"index":4}},{"kind":"Function","span":{"file_name":"src/main.rs","byte_start":148,"byte_end":155,"line_start":8,"line_end":8,"column_start":31,"column_end":38},"ref_id":{"krate":2,"index":7290}},{"kind":"Type","span":{"file_name":"src/main.rs","byte_start":139,"byte_end":146,"line_start":8,"line_end":8,"column_start":22,"column_end":29},"ref_id":{"krate":2,"index":38304}},{"kind":"Variable","span":{"file_name":"src/main.rs","byte_start":139,"byte_end":140,"line_start":8,"line_end":8,"column_start":22,"column_end":23},"ref_id":{"krate":2,"index":38306}},{"kind":"Variable","span":{"file_name":"src/main.rs","byte_start":142,"byte_end":146,"line_start":8,"line_end":8,"column_start":25,"column_end":29},"ref_id":{"krate":2,"index":38307}},{"kind":"Variable","span":{"file_name":"src/main.rs","byte_start":142,"byte_end":146,"line_start":8,"line_end":8,"column_start":25,"column_end":29},"ref_id":{"krate":0,"index":1073741830}},{"kind":"Variable","span":{"file_name":"src/main.rs","byte_start":258,"byte_end":262,"line_start":13,"line_end":13,"column_start":33,"column_end":37},"ref_id":{"krate":0,"index":1073741831}},{"kind":"Variable","span":{"file_name":"src/main.rs","byte_start":263,"byte_end":269,"line_start":13,"line_end":13,"column_start":38,"column_end":44},"ref_id":{"krate":0,"index":4}},{"kind":"Variable","span":{"file_name":"src/main.rs","byte_start":270,"byte_end":277,"line_start":13,"line_end":13,"column_start":45,"column_end":52},"ref_id":{"krate":0,"index":536870919}},{"kind":"Variable","span":{"file_name":"src/main.rs","byte_start":291,"byte_end":308,"line_start":14,"line_end":14,"column_start":12,"column_end":29},"ref_id":{"krate":0,"index":805306375}},{"kind":"Variable","span":{"file_name":"src/main.rs","byte_start":312,"byte_end":319,"line_start":14,"line_end":14,"column_start":33,"column_end":40},"ref_id":{"krate":0,"index":536870919}},{"kind":"Function","span":{"file_name":"src/main.rs","byte_start":362,"byte_end":366,"line_start":15,"line_end":15,"column_start":41,"column_end":45},"ref_id":{"krate":0,"index":7}},{"kind":"Variable","span":{"file_name":"src/main.rs","byte_start":357,"byte_end":361,"line_start":15,"line_end":15,"column_start":36,"column_end":40},"ref_id":{"krate":0,"index":1073741831}},{"kind":"Variable","span":{"file_name":"src/main.rs","byte_start":367,"byte_end":384,"line_start":15,"line_end":15,"column_start":46,"column_end":63},"ref_id":{"krate":0,"index":805306375}},{"kind":"Variable","span":{"file_name":"src/main.rs","byte_start":334,"byte_end":338,"line_start":15,"line_end":15,"column_start":13,"column_end":17},"ref_id":{"krate":0,"index":1073741831}},{"kind":"Variable","span":{"file_name":"src/main.rs","byte_start":339,"byte_end":345,"line_start":15,"line_end":15,"column_start":18,"column_end":24},"ref_id":{"krate":0,"index":4}},{"kind":"Variable","span":{"file_name":"src/main.rs","byte_start":346,"byte_end":353,"line_start":15,"line_end":15,"column_start":25,"column_end":32},"ref_id":{"krate":0,"index":536870919}},{"kind":"Variable","span":{"file_name":"src/main.rs","byte_start":414,"byte_end":418,"line_start":18,"line_end":18,"column_start":9,"column_end":13},"ref_id":{"krate":0,"index":1073741831}},{"kind":"Variable","span":{"file_name":"src/main.rs","byte_start":419,"byte_end":425,"line_start":18,"line_end":18,"column_start":14,"column_end":20},"ref_id":{"krate":0,"index":4}},{"kind":"Variable","span":{"file_name":"src/main.rs","byte_start":426,"byte_end":433,"line_start":18,"line_end":18,"column_start":21,"column_end":28},"ref_id":{"krate":0,"index":536870919}},{"kind":"Function","span":{"file_name":"src/main.rs","byte_start":547,"byte_end":551,"line_start":22,"line_end":22,"column_start":48,"column_end":52},"ref_id":{"krate":0,"index":7}},{"kind":"Variable","span":{"file_name":"src/main.rs","byte_start":542,"byte_end":546,"line_start":22,"line_end":22,"column_start":43,"column_end":47},"ref_id":{"krate":0,"index":1073741832}},{"kind":"Variable","span":{"file_name":"src/main.rs","byte_start":552,"byte_end":553,"line_start":22,"line_end":22,"column_start":53,"column_end":54},"ref_id":{"krate":0,"index":536870920}},{"kind":"Function","span":{"file_name":"src/main.rs","byte_start":561,"byte_end":565,"line_start":22,"line_end":22,"column_start":62,"column_end":66},"ref_id":{"krate":0,"index":7}},{"kind":"Variable","span":{"file_name":"src/main.rs","byte_start":556,"byte_end":560,"line_start":22,"line_end":22,"column_start":57,"column_end":61},"ref_id":{"krate":0,"index":1073741832}},{"kind":"Variable","span":{"file_name":"src/main.rs","byte_start":566,"byte_end":567,"line_start":22,"line_end":22,"column_start":67,"column_end":68},"ref_id":{"krate":0,"index":2684354568}},{"kind":"Variable","span":{"file_name":"src/main.rs","byte_start":606,"byte_end":617,"line_start":23,"line_end":23,"column_start":36,"column_end":47},"ref_id":{"krate":0,"index":1744830472}},{"kind":"Variable","span":{"file_name":"src/main.rs","byte_start":579,"byte_end":583,"line_start":23,"line_end":23,"column_start":9,"column_end":13},"ref_id":{"krate":0,"index":1073741832}},{"kind":"Variable","span":{"file_name":"src/main.rs","byte_start":584,"byte_end":590,"line_start":23,"line_end":23,"column_start":14,"column_end":20},"ref_id":{"krate":0,"index":4}},{"kind":"Variable","span":{"file_name":"src/main.rs","byte_start":591,"byte_end":602,"line_start":23,"line_end":23,"column_start":21,"column_end":32},"ref_id":{"krate":0,"index":2818572296}},{"kind":"Variable","span":{"file_name":"src/main.rs","byte_start":627,"byte_end":638,"line_start":24,"line_end":24,"column_start":9,"column_end":20},"ref_id":{"krate":0,"index":2818572296}},{"kind":"Variable","span":{"file_name":"src/main.rs","byte_start":642,"byte_end":653,"line_start":24,"line_end":24,"column_start":24,"column_end":35},"ref_id":{"krate":0,"index":1744830472}},{"kind":"Type","span":{"file_name":"src/main.rs","byte_start":714,"byte_end":719,"line_start":30,"line_end":30,"column_start":16,"column_end":21},"ref_id":{"krate":0,"index":18}},{"kind":"Type","span":{"file_name":"src/main.rs","byte_start":736,"byte_end":742,"line_start":31,"line_end":31,"column_start":16,"column_end":22},"ref_id":{"krate":2,"index":39710}},{"kind":"Type","span":{"file_name":"src/main.rs","byte_start":776,"byte_end":797,"line_start":34,"line_end":34,"column_start":23,"column_end":44},"ref_id":{"krate":0,"index":9}},{"kind":"Type","span":{"file_name":"src/main.rs","byte_start":763,"byte_end":771,"line_start":34,"line_end":34,"column_start":10,"column_end":18},"ref_id":{"krate":2,"index":7233}},{"kind":"Type","span":{"file_name":"src/main.rs","byte_start":863,"byte_end":869,"line_start":37,"line_end":37,"column_start":27,"column_end":33},"ref_id":{"krate":2,"index":39710}},{"kind":"Function","span":{"file_name":"src/main.rs","byte_start":907,"byte_end":910,"line_start":38,"line_end":38,"column_start":24,"column_end":27},"ref_id":{"krate":2,"index":7679}},{"kind":"Variable","span":{"file_name":"src/main.rs","byte_start":892,"byte_end":896,"line_start":38,"line_end":38,"column_start":9,"column_end":13},"ref_id":{"krate":0,"index":1073741840}},{"kind":"Variable","span":{"file_name":"src/main.rs","byte_start":897,"byte_end":906,"line_start":38,"line_end":38,"column_start":14,"column_end":23},"ref_id":{"krate":0,"index":12}},{"kind":"Variable","span":{"file_name":"src/main.rs","byte_start":945,"byte_end":949,"line_start":39,"line_end":39,"column_start":26,"column_end":30},"ref_id":{"krate":0,"index":1073741840}},{"kind":"Variable","span":{"file_name":"src/main.rs","byte_start":950,"byte_end":955,"line_start":39,"line_end":39,"column_start":31,"column_end":36},"ref_id":{"krate":0,"index":11}},{"kind":"Variable","span":{"file_name":"src/main.rs","byte_start":956,"byte_end":970,"line_start":39,"line_end":39,"column_start":37,"column_end":51},"ref_id":{"krate":0,"index":21}},{"kind":"Variable","span":{"file_name":"src/main.rs","byte_start":971,"byte_end":975,"line_start":39,"line_end":39,"column_start":52,"column_end":56},"ref_id":{"krate":0,"index":268435472}},{"kind":"Variable","span":{"file_name":"src/main.rs","byte_start":1007,"byte_end":1011,"line_start":40,"line_end":40,"column_start":30,"column_end":34},"ref_id":{"krate":0,"index":1073741840}},{"kind":"Variable","span":{"file_name":"src/main.rs","byte_start":1012,"byte_end":1017,"line_start":40,"line_end":40,"column_start":35,"column_end":40},"ref_id":{"krate":0,"index":11}},{"kind":"Variable","span":{"file_name":"src/main.rs","byte_start":1018,"byte_end":1030,"line_start":40,"line_end":40,"column_start":41,"column_end":53},"ref_id":{"krate":0,"index":20}},{"kind":"Variable","span":{"file_name":"src/main.rs","byte_start":1031,"byte_end":1035,"line_start":40,"line_end":40,"column_start":54,"column_end":58},"ref_id":{"krate":0,"index":268435472}},{"kind":"Variable","span":{"file_name":"src/main.rs","byte_start":990,"byte_end":994,"line_start":40,"line_end":40,"column_start":13,"column_end":17},"ref_id":{"krate":0,"index":1073741840}},{"kind":"Variable","span":{"file_name":"src/main.rs","byte_start":995,"byte_end":1004,"line_start":40,"line_end":40,"column_start":18,"column_end":27},"ref_id":{"krate":0,"index":12}},{"kind":"Variable","span":{"file_name":"src/main.rs","byte_start":1051,"byte_end":1055,"line_start":41,"line_end":41,"column_start":14,"column_end":18},"ref_id":{"krate":0,"index":268435472}},{"kind":"Variable","span":{"file_name":"src/main.rs","byte_start":1057,"byte_end":1063,"line_start":41,"line_end":41,"column_start":20,"column_end":26},"ref_id":{"krate":0,"index":2281701392}},{"kind":"Type","span":{"file_name":"src/main.rs","byte_start":1120,"byte_end":1123,"line_start":47,"line_end":47,"column_start":21,"column_end":24},"ref_id":{"krate":5,"index":6772}},{"kind":"Type","span":{"file_name":"src/main.rs","byte_start":1124,"byte_end":1130,"line_start":47,"line_end":47,"column_start":25,"column_end":31},"ref_id":{"krate":2,"index":39710}},{"kind":"Type","span":{"file_name":"src/main.rs","byte_start":1158,"byte_end":1161,"line_start":48,"line_end":48,"column_start":19,"column_end":22},"ref_id":{"krate":5,"index":6772}},{"kind":"Type","span":{"file_name":"src/main.rs","byte_start":1162,"byte_end":1168,"line_start":48,"line_end":48,"column_start":23,"column_end":29},"ref_id":{"krate":2,"index":39710}},{"kind":"Type","span":{"file_name":"src/main.rs","byte_start":1198,"byte_end":1201,"line_start":49,"line_end":49,"column_start":21,"column_end":24},"ref_id":{"krate":5,"index":6772}},{"kind":"Type","span":{"file_name":"src/main.rs","byte_start":1218,"byte_end":1223,"line_start":52,"line_end":52,"column_start":6,"column_end":11},"ref_id":{"krate":0,"index":18}},{"kind":"Type","span":{"file_name":"src/main.rs","byte_start":1298,"byte_end":1302,"line_start":54,"line_end":54,"column_start":9,"column_end":13},"ref_id":{"krate":0,"index":18}},{"kind":"Variable","span":{"file_name":"src/main.rs","byte_start":1317,"byte_end":1331,"line_start":55,"line_end":55,"column_start":13,"column_end":27},"ref_id":{"krate":0,"index":19}},{"kind":"Type","span":{"file_name":"src/main.rs","byte_start":1338,"byte_end":1342,"line_start":55,"line_end":55,"column_start":34,"column_end":38},"ref_id":{"krate":2,"index":39712}},{"kind":"Variable","span":{"file_name":"src/main.rs","byte_start":1344,"byte_end":1356,"line_start":55,"line_end":55,"column_start":40,"column_end":52},"ref_id":{"krate":0,"index":1073741847}},{"kind":"Variable","span":{"file_name":"src/main.rs","byte_start":1371,"byte_end":1383,"line_start":56,"line_end":56,"column_start":13,"column_end":25},"ref_id":{"krate":0,"index":20}},{"kind":"Function","span":{"file_name":"src/main.rs","byte_start":1390,"byte_end":1403,"line_start":56,"line_end":56,"column_start":32,"column_end":45},"ref_id":{"krate":5,"index":6780}},{"kind":"Type","span":{"file_name":"src/main.rs","byte_start":1385,"byte_end":1388,"line_start":56,"line_end":56,"column_start":27,"column_end":30},"ref_id":{"krate":5,"index":6772}},{"kind":"Variable","span":{"file_name":"src/main.rs","byte_start":1404,"byte_end":1417,"line_start":56,"line_end":56,"column_start":46,"column_end":59},"ref_id":{"krate":0,"index":536870935}},{"kind":"Variable","span":{"file_name":"src/main.rs","byte_start":1432,"byte_end":1446,"line_start":57,"line_end":57,"column_start":13,"column_end":27},"ref_id":{"krate":0,"index":21}},{"kind":"Function","span":{"file_name":"src/main.rs","byte_start":1453,"byte_end":1466,"line_start":57,"line_end":57,"column_start":34,"column_end":47},"ref_id":{"krate":5,"index":6780}},{"kind":"Type","span":{"file_name":"src/main.rs","byte_start":1448,"byte_end":1451,"line_start":57,"line_end":57,"column_start":29,"column_end":32},"ref_id":{"krate":5,"index":6772}},{"kind":"Variable","span":{"file_name":"src/main.rs","byte_start":1467,"byte_end":1480,"line_start":57,"line_end":57,"column_start":48,"column_end":61},"ref_id":{"krate":0,"index":536870935}},{"kind":"Function","span":{"file_name":"src/main.rs","byte_start":1575,"byte_end":1578,"line_start":63,"line_end":63,"column_start":29,"column_end":32},"ref_id":{"krate":5,"index":6850}},{"kind":"Variable","span":{"file_name":"src/main.rs","byte_start":1555,"byte_end":1559,"line_start":63,"line_end":63,"column_start":9,"column_end":13},"ref_id":{"krate":0,"index":1073741848}},{"kind":"Variable","span":{"file_name":"src/main.rs","byte_start":1560,"byte_end":1574,"line_start":63,"line_end":63,"column_start":14,"column_end":28},"ref_id":{"krate":0,"index":19}},{"kind":"Function","span":{"file_name":"src/main.rs","byte_start":1655,"byte_end":1658,"line_start":67,"line_end":67,"column_start":29,"column_end":32},"ref_id":{"krate":5,"index":6850}},{"kind":"Variable","span":{"file_name":"src/main.rs","byte_start":1635,"byte_end":1639,"line_start":67,"line_end":67,"column_start":9,"column_end":13},"ref_id":{"krate":0,"index":1073741849}},{"kind":"Variable","span":{"file_name":"src/main.rs","byte_start":1640,"byte_end":1654,"line_start":67,"line_end":67,"column_start":14,"column_end":28},"ref_id":{"krate":0,"index":21}},{"kind":"Function","span":{"file_name":"src/main.rs","byte_start":1756,"byte_end":1760,"line_start":71,"line_end":71,"column_start":27,"column_end":31},"ref_id":{"krate":5,"index":6843}},{"kind":"Variable","span":{"file_name":"src/main.rs","byte_start":1738,"byte_end":1742,"line_start":71,"line_end":71,"column_start":9,"column_end":13},"ref_id":{"krate":0,"index":1073741850}},{"kind":"Variable","span":{"file_name":"src/main.rs","byte_start":1743,"byte_end":1755,"line_start":71,"line_end":71,"column_start":14,"column_end":26},"ref_id":{"krate":0,"index":20}},{"kind":"Variable","span":{"file_name":"src/main.rs","byte_start":1761,"byte_end":1765,"line_start":71,"line_end":71,"column_start":32,"column_end":36},"ref_id":{"krate":0,"index":1073741850}},{"kind":"Variable","span":{"file_name":"src/main.rs","byte_start":1766,"byte_end":1780,"line_start":71,"line_end":71,"column_start":37,"column_end":51},"ref_id":{"krate":0,"index":19}},{"kind":"Variable","span":{"file_name":"src/main.rs","byte_start":1781,"byte_end":1782,"line_start":71,"line_end":71,"column_start":52,"column_end":53},"ref_id":{"krate":0,"index":536870938}},{"kind":"Type","span":{"file_name":"src/main.rs","byte_start":1819,"byte_end":1823,"line_start":72,"line_end":72,"column_start":34,"column_end":38},"ref_id":{"krate":2,"index":39714}},{"kind":"Function","span":{"file_name":"src/main.rs","byte_start":1829,"byte_end":1842,"line_start":72,"line_end":72,"column_start":44,"column_end":57},"ref_id":{"krate":0,"index":25}},{"kind":"Variable","span":{"file_name":"src/main.rs","byte_start":1824,"byte_end":1828,"line_start":72,"line_end":72,"column_start":39,"column_end":43},"ref_id":{"krate":0,"index":1073741850}},{"kind":"Variable","span":{"file_name":"src/main.rs","byte_start":1794,"byte_end":1798,"line_start":72,"line_end":72,"column_start":9,"column_end":13},"ref_id":{"krate":0,"index":1073741850}},{"kind":"Variable","span":{"file_name":"src/main.rs","byte_start":1799,"byte_end":1813,"line_start":72,"line_end":72,"column_start":14,"column_end":28},"ref_id":{"krate":0,"index":19}},{"kind":"Variable","span":{"file_name":"src/main.rs","byte_start":1814,"byte_end":1815,"line_start":72,"line_end":72,"column_start":29,"column_end":30},"ref_id":{"krate":0,"index":536870938}},{"kind":"Function","span":{"file_name":"src/main.rs","byte_start":1875,"byte_end":1879,"line_start":73,"line_end":73,"column_start":29,"column_end":33},"ref_id":{"krate":5,"index":6843}},{"kind":"Variable","span":{"file_name":"src/main.rs","byte_start":1855,"byte_end":1859,"line_start":73,"line_end":73,"column_start":9,"column_end":13},"ref_id":{"krate":0,"index":1073741850}},{"kind":"Variable","span":{"file_name":"src/main.rs","byte_start":1860,"byte_end":1874,"line_start":73,"line_end":73,"column_start":14,"column_end":28},"ref_id":{"krate":0,"index":21}},{"kind":"Variable","span":{"file_name":"src/main.rs","byte_start":1880,"byte_end":1881,"line_start":73,"line_end":73,"column_start":34,"column_end":35},"ref_id":{"krate":0,"index":2684354586}},{"kind":"Function","span":{"file_name":"src/main.rs","byte_start":1968,"byte_end":1985,"line_start":77,"line_end":77,"column_start":14,"column_end":31},"ref_id":{"krate":0,"index":26}},{"kind":"Variable","span":{"file_name":"src/main.rs","byte_start":1963,"byte_end":1967,"line_start":77,"line_end":77,"column_start":9,"column_end":13},"ref_id":{"krate":0,"index":1073741851}},{"kind":"Variable","span":{"file_name":"src/main.rs","byte_start":1987,"byte_end":1988,"line_start":77,"line_end":77,"column_start":33,"column_end":34},"ref_id":{"krate":0,"index":536870939}},{"kind":"Variable","span":{"file_name":"src/main.rs","byte_start":1989,"byte_end":1990,"line_start":77,"line_end":77,"column_start":35,"column_end":36},"ref_id":{"krate":0,"index":2684354587}},{"kind":"Function","span":{"file_name":"src/main.rs","byte_start":2007,"byte_end":2024,"line_start":78,"line_end":78,"column_start":14,"column_end":31},"ref_id":{"krate":0,"index":26}},{"kind":"Variable","span":{"file_name":"src/main.rs","byte_start":2002,"byte_end":2006,"line_start":78,"line_end":78,"column_start":9,"column_end":13},"ref_id":{"krate":0,"index":1073741851}},{"kind":"Variable","span":{"file_name":"src/main.rs","byte_start":2026,"byte_end":2027,"line_start":78,"line_end":78,"column_start":33,"column_end":34},"ref_id":{"krate":0,"index":2684354587}},{"kind":"Variable","span":{"file_name":"src/main.rs","byte_start":2028,"byte_end":2029,"line_start":78,"line_end":78,"column_start":35,"column_end":36},"ref_id":{"krate":0,"index":536870939}},{"kind":"Function","span":{"file_name":"src/main.rs","byte_start":2117,"byte_end":2134,"line_start":82,"line_end":82,"column_start":14,"column_end":31},"ref_id":{"krate":0,"index":26}},{"kind":"Variable","span":{"file_name":"src/main.rs","byte_start":2112,"byte_end":2116,"line_start":82,"line_end":82,"column_start":9,"column_end":13},"ref_id":{"krate":0,"index":1073741852}},{"kind":"Variable","span":{"file_name":"src/main.rs","byte_start":2136,"byte_end":2137,"line_start":82,"line_end":82,"column_start":33,"column_end":34},"ref_id":{"krate":0,"index":536870940}},{"kind":"Variable","span":{"file_name":"src/main.rs","byte_start":2143,"byte_end":2144,"line_start":82,"line_end":82,"column_start":40,"column_end":41},"ref_id":{"krate":0,"index":1610612764}},{"kind":"Function","span":{"file_name":"src/main.rs","byte_start":2161,"byte_end":2178,"line_start":83,"line_end":83,"column_start":14,"column_end":31},"ref_id":{"krate":0,"index":26}},{"kind":"Variable","span":{"file_name":"src/main.rs","byte_start":2156,"byte_end":2160,"line_start":83,"line_end":83,"column_start":9,"column_end":13},"ref_id":{"krate":0,"index":1073741852}},{"kind":"Variable","span":{"file_name":"src/main.rs","byte_start":2180,"byte_end":2181,"line_start":83,"line_end":83,"column_start":33,"column_end":34},"ref_id":{"krate":0,"index":1610612764}},{"kind":"Variable","span":{"file_name":"src/main.rs","byte_start":2187,"byte_end":2188,"line_start":83,"line_end":83,"column_start":40,"column_end":41},"ref_id":{"krate":0,"index":536870940}},{"kind":"Type","span":{"file_name":"src/main.rs","byte_start":2245,"byte_end":2266,"line_start":86,"line_end":86,"column_start":47,"column_end":68},"ref_id":{"krate":0,"index":9}},{"kind":"Type","span":{"file_name":"src/main.rs","byte_start":2277,"byte_end":2298,"line_start":87,"line_end":87,"column_start":9,"column_end":30},"ref_id":{"krate":0,"index":9}},{"kind":"Variable","span":{"file_name":"src/main.rs","byte_start":2313,"byte_end":2318,"line_start":88,"line_end":88,"column_start":13,"column_end":18},"ref_id":{"krate":0,"index":11}},{"kind":"Variable","span":{"file_name":"src/main.rs","byte_start":2320,"byte_end":2324,"line_start":88,"line_end":88,"column_start":20,"column_end":24},"ref_id":{"krate":0,"index":1073741853}},{"kind":"Variable","span":{"file_name":"src/main.rs","byte_start":2338,"byte_end":2347,"line_start":89,"line_end":89,"column_start":13,"column_end":22},"ref_id":{"krate":0,"index":12}},{"kind":"Variable","span":{"file_name":"src/main.rs","byte_start":2349,"byte_end":2353,"line_start":89,"line_end":89,"column_start":24,"column_end":28},"ref_id":{"krate":0,"index":1073741853}},{"kind":"Variable","span":{"file_name":"src/main.rs","byte_start":2354,"byte_end":2368,"line_start":89,"line_end":89,"column_start":29,"column_end":43},"ref_id":{"krate":0,"index":19}},{"kind":"Variable","span":{"file_name":"src/main.rs","byte_start":2369,"byte_end":2370,"line_start":89,"line_end":89,"column_start":44,"column_end":45},"ref_id":{"krate":0,"index":536870941}},{"kind":"Type","span":{"file_name":"src/main.rs","byte_start":2450,"byte_end":2453,"line_start":98,"line_end":98,"column_start":16,"column_end":19},"ref_id":{"krate":5,"index":6772}},{"kind":"Function","span":{"file_name":"src/main.rs","byte_start":2553,"byte_end":2556,"line_start":99,"line_end":99,"column_start":28,"column_end":31},"ref_id":{"krate":0,"index":23}},{"kind":"Type","span":{"file_name":"src/main.rs","byte_start":2546,"byte_end":2551,"line_start":99,"line_end":99,"column_start":21,"column_end":26},"ref_id":{"krate":0,"index":18}},{"kind":"Variable","span":{"file_name":"src/main.rs","byte_start":2579,"byte_end":2580,"line_start":100,"line_end":100,"column_start":14,"column_end":15},"ref_id":{"krate":2,"index":38306}},{"kind":"Variable","span":{"file_name":"src/main.rs","byte_start":2582,"byte_end":2593,"line_start":100,"line_end":100,"column_start":17,"column_end":28},"ref_id":{"krate":2,"index":38307}},{"kind":"Function","span":{"file_name":"src/main.rs","byte_start":2588,"byte_end":2591,"line_start":100,"line_end":100,"column_start":23,"column_end":26},"ref_id":{"krate":5,"index":6850}},{"kind":"Variable","span":{"file_name":"src/main.rs","byte_start":2582,"byte_end":2587,"line_start":100,"line_end":100,"column_start":17,"column_end":22},"ref_id":{"krate":0,"index":1140850718}},{"kind":"Variable","span":{"file_name":"src/main.rs","byte_start":2574,"byte_end":2575,"line_start":100,"line_end":100,"column_start":9,"column_end":10},"ref_id":{"krate":2,"index":39716}},{"kind":"Variable","span":{"file_name":"src/main.rs","byte_start":2607,"byte_end":2608,"line_start":101,"line_end":101,"column_start":12,"column_end":13},"ref_id":{"krate":0,"index":838860830}},{"kind":"Function","span":{"file_name":"src/main.rs","byte_start":2639,"byte_end":2656,"line_start":102,"line_end":102,"column_start":20,"column_end":37},"ref_id":{"krate":0,"index":26}},{"kind":"Variable","span":{"file_name":"src/main.rs","byte_start":2632,"byte_end":2637,"line_start":102,"line_end":102,"column_start":13,"column_end":18},"ref_id":{"krate":0,"index":872415262}},{"kind":"Variable","span":{"file_name":"src/main.rs","byte_start":2657,"byte_end":2662,"line_start":102,"line_end":102,"column_start":38,"column_end":43},"ref_id":{"krate":0,"index":1140850718}},{"kind":"Variable","span":{"file_name":"src/main.rs","byte_start":2663,"byte_end":2664,"line_start":102,"line_end":102,"column_start":44,"column_end":45},"ref_id":{"krate":0,"index":838860830}},{"kind":"Function","span":{"file_name":"src/main.rs","byte_start":2703,"byte_end":2722,"line_start":104,"line_end":104,"column_start":19,"column_end":38},"ref_id":{"krate":0,"index":27}},{"kind":"Variable","span":{"file_name":"src/main.rs","byte_start":2697,"byte_end":2702,"line_start":104,"line_end":104,"column_start":13,"column_end":18},"ref_id":{"krate":0,"index":872415262}},{"kind":"Variable","span":{"file_name":"src/main.rs","byte_start":2723,"byte_end":2728,"line_start":104,"line_end":104,"column_start":39,"column_end":44},"ref_id":{"krate":0,"index":1140850718}},{"kind":"Variable","span":{"file_name":"src/main.rs","byte_start":2729,"byte_end":2730,"line_start":104,"line_end":104,"column_start":45,"column_end":46},"ref_id":{"krate":0,"index":838860830}},{"kind":"Function","span":{"file_name":"src/main.rs","byte_start":2799,"byte_end":2806,"line_start":108,"line_end":108,"column_start":49,"column_end":56},"ref_id":{"krate":2,"index":7290}},{"kind":"Type","span":{"file_name":"src/main.rs","byte_start":2809,"byte_end":2812,"line_start":108,"line_end":108,"column_start":59,"column_end":62},"ref_id":{"krate":5,"index":6772}},{"kind":"Function","span":{"file_name":"src/main.rs","byte_start":2777,"byte_end":2795,"line_start":108,"line_end":108,"column_start":27,"column_end":45},"ref_id":{"krate":0,"index":29}},{"kind":"Variable","span":{"file_name":"src/main.rs","byte_start":2771,"byte_end":2776,"line_start":108,"line_end":108,"column_start":21,"column_end":26},"ref_id":{"krate":0,"index":872415262}},{"kind":"Variable","span":{"file_name":"src/main.rs","byte_start":2835,"byte_end":2844,"line_start":109,"line_end":109,"column_start":16,"column_end":25},"ref_id":{"krate":0,"index":3238002718}},{"kind":"Variable","span":{"file_name":"src/main.rs","byte_start":2900,"byte_end":2909,"line_start":111,"line_end":111,"column_start":27,"column_end":36},"ref_id":{"krate":0,"index":3238002718}},{"kind":"Variable","span":{"file_name":"src/main.rs","byte_start":2882,"byte_end":2896,"line_start":111,"line_end":111,"column_start":9,"column_end":23},"ref_id":{"krate":2,"index":39716}},{"kind":"Variable","span":{"file_name":"src/main.rs","byte_start":2931,"byte_end":2937,"line_start":112,"line_end":112,"column_start":20,"column_end":26},"ref_id":{"krate":0,"index":1191182366}},{"kind":"Variable","span":{"file_name":"src/main.rs","byte_start":2939,"byte_end":2944,"line_start":112,"line_end":112,"column_start":28,"column_end":33},"ref_id":{"krate":0,"index":872415262}},{"kind":"Variable","span":{"file_name":"src/main.rs","byte_start":2945,"byte_end":2959,"line_start":112,"line_end":112,"column_start":34,"column_end":48},"ref_id":{"krate":0,"index":21}},{"kind":"Variable","span":{"file_name":"src/main.rs","byte_start":2960,"byte_end":2964,"line_start":112,"line_end":112,"column_start":49,"column_end":53},"ref_id":{"krate":0,"index":2264924190}}],"macro_refs":[],"relations":[{"span":{"file_name":"src/main.rs","byte_start":54,"byte_end":66,"line_start":5,"line_end":5,"column_start":6,"column_end":18},"kind":{"Impl":{"id":0}},"from":{"krate":0,"index":3},"to":{"krate":4294967295,"index":4294967295}},{"span":{"file_name":"src/main.rs","byte_start":776,"byte_end":797,"line_start":34,"line_end":34,"column_start":23,"column_end":44},"kind":{"Impl":{"id":1}},"from":{"krate":0,"index":9},"to":{"krate":2,"index":7233}},{"span":{"file_name":"src/main.rs","byte_start":1218,"byte_end":1223,"line_start":52,"line_end":52,"column_start":6,"column_end":11},"kind":{"Impl":{"id":2}},"from":{"krate":0,"index":18},"to":{"krate":4294967295,"index":4294967295}}]}